identity_client/__init__.py
identity_client/api_key_auth.py
identity_client/helpers.py
identity_client/identity_session_auth.py
identity_client/signed_cookies.py
identity_client/views.py
identity_client-1.0.34.dist-info/METADATA
identity_client-1.0.34.dist-info/WHEEL
identity_client-1.0.34.dist-info/RECORD
